litemodel_starlette/__init__.py
litemodel_starlette/admin.py
litemodel_starlette/models.py
litemodel_starlette/py.typed
litemodel_starlette/resources.py
litemodel_starlette/settings.py
litemodel_starlette/utils.py
litemodel_starlette/views.py
litemodel_starlette/templates/_admin_base.html
litemodel_starlette/templates/_admin_footer.html
litemodel_starlette/templates/_admin_header.hml
litemodel_starlette/templates/admin_detail.html
litemodel_starlette/templates/admin_edit.html
litemodel_starlette/templates/admin_index.html
litemodel_starlette/templates/admin_list.html
litemodel_starlette/templates/admin_login.html
litemodel_starlette/templates/admin_logout.html
litemodel_starlette/templates/admin_new.html
litemodel_starlette-0.1.5.dist-info/METADATA
litemodel_starlette-0.1.5.dist-info/WHEEL
litemodel_starlette-0.1.5.dist-info/RECORD
