Metadata-Version: 2.4
Name: litemodel-starlette
Version: 0.1.5
Summary: Add your description here
Author-email: Joe Pasquantonio <joe.pasquantonio@gmail.com>
Requires-Python: >=3.11
Requires-Dist: bcrypt>=4.2.1
Requires-Dist: databases[aiosqlite]>=0.9.0
Requires-Dist: litemodel>=0.1.2
Requires-Dist: starlette-login>=1.0.2
Requires-Dist: starlette>=0.42.0
